{"character": "兄", "strokes": "5", "radical": "儿", "radical variants": [], "radical meaning": ["legs"], "parts": ["儿", "口"], "kanji_variants": "", "meanings": ["elder brother", "big brother"], "kun": ["あに"], "on": ["ケイ", "キョウ"], "nanori readings": ["え", "せ", "よし"], "grade": "Jōyō kanji, taught in grade 2", "jlpt": "N4", "frequency": "1219", "on reading compounds": ["兄【ケイ】elder brother, pronoun or suffix used in reference to an older brother figure, Mister, Mr", "兄弟【キョウダイ】siblings, brothers and sisters, brothers, siblings-in-law, brothers-in-law, sisters-in-law, mate, friend", "実兄【ジッケイ】biological older brother", "父兄【フケイ】guardians, parents, father and older brother", "兄弟【キョウダイ】siblings, brothers and sisters, brothers, siblings-in-law, brothers-in-law, sisters-in-law, mate, friend", "兄姉【ケイシ】brother and sister"], "kun reading compounds": ["兄【あに】elder brother, older brother", "兄貴【あにき】elder brother, one's senior, older man, man older than oneself", "中の兄【なかのあに】middle brother", "義理の兄【ぎりのあに】one's brother-in-law, stepbrother (elder)"]}