{"character": "陸", "strokes": "11", "radical": "阝", "radical variants": ["阜", "阝"], "radical meaning": ["mound", "dam (阝 left)"], "parts": ["儿", "土", "阡"], "kanji_variants": "", "meanings": ["land", "six"], "kun": ["おか"], "on": ["リク", "ロク"], "nanori readings": ["くが", "たち", "みち", "む", "むつ"], "grade": "Jōyō kanji, taught in grade 4", "jlpt": "N2", "frequency": "736", "on reading compounds": ["陸【リク】land, shore", "陸海【リクカイ】land and sea", "北陸【ホクリク】Hokuriku region of Honshu (incl. Niigata, Toyama, Ishikawa and Fukui prefectures)", "内陸【ナイリク】inland", "六【ロク】six", "碌【ロク】satisfactory, decent, good, proper, worthy", "碌碌【ロクロク】hardly, barely, inadequately (with negative grammatical constructions)", "双六【スゴロク】sugoroku, traditional Japanese board game played with dice"], "kun reading compounds": ["陸【りく】land, shore", "丘【おか】hill, height, knoll, rising ground, bonus points awarded to the winner at the end of a game"]}