{"character": "憂", "strokes": "15", "radical": "心", "radical variants": ["忄", "⺗"], "radical meaning": ["heart"], "parts": ["一", "冖", "夂", "心", "白", "自"], "kanji_variants": "", "meanings": ["melancholy", "grieve", "lament", "be anxious", "sad", "unhappy"], "kun": ["うれ.える", "うれ.い", "う.い", "う.き"], "on": ["ユウ"], "nanori readings": ["ゆ"], "grade": "Jōyō kanji, taught in junior high", "jlpt": "N1", "frequency": "1625", "on reading compounds": ["憂慮【ユウリョ】anxiety, concern, fear", "憂鬱【ユウウツ】depression, melancholy, dejection, gloom, despondency", "外憂【ガイユウ】external troubles, foreign threat", "内憂【ナイユウ】internal troubles, domestic discord"], "kun reading compounds": ["憂える【うれえる】to worry about, to be anxious about, to be concerned about, to lament, to grieve, to feel sorrow for", "憂い【うれい】sorrow, grief, anguish, distress, trouble, affliction, anxiety, fear, misgivings", "憂い顔【うれいがお】sad face, sorrowful face, anxious look, sad countenance", "憂い【うい】unhappy, sad, gloomy", "憂き【うき】unhappy, sad, gloomy", "憂き目【うきめ】bitter experience, misery, distress, grief, sad thoughts, hardship"]}