{"character": "板", "strokes": "8", "radical": "木", "radical variants": [], "radical meaning": ["tree"], "parts": ["厂", "又", "木"], "kanji_variants": "", "meanings": ["plank", "board", "plate", "stage"], "kun": ["いた"], "on": ["ハン", "バン"], "nanori readings": "", "grade": "Jōyō kanji, taught in grade 3", "jlpt": "N2", "frequency": "926", "on reading compounds": ["板門店【パンムンジョム】Panmunjon (Korea), Joint Security Area (Korean Demilitarized Zone)", "版画【ハンガ】woodcut, woodblock print, art print", "合板【ゴウハン】veneer board, plywood, joint publication", "鋼板【コウハン】steel sheet, steel plate, steel plates", "版木【ハンギ】(printing) block, woodcut", "板金【バンキン】sheet metal, metal plate", "鋼板【コウハン】steel sheet, steel plate, steel plates", "降板【コウバン】leaving the mound, being knocked out, resigning from a role or position"], "kun reading compounds": ["板【いた】board, plank, sheet (of metal), plate (of glass), pane, slab, cutting board, chopping board, chef (esp. of high-end Japanese cuisine), cook, stage (i.e. at a theatre)", "板ガラス【いたガラス】plate glass, sheet glass", "まな板【まないた】chopping board, cutting board", "厚板【あついた】plank, thick board, plate glass, heavy metal sheet (esp. welding), heavy brocaded obi"]}