{"character": "礁", "strokes": "17", "radical": "石", "radical variants": [], "radical meaning": ["stone"], "parts": ["口", "杰", "石", "隹"], "kanji_variants": "", "meanings": ["reef", "sunken rock"], "kun": "", "on": ["ショウ"], "nanori readings": "", "grade": "Jōyō kanji, taught in junior high", "jlpt": "N1", "frequency": "1977", "on reading compounds": ["礁湖【ショウコ】barrier lagoon, coral-reef lagoon", "環礁【カンショウ】atoll, circular coral reef", "座礁【ザショウ】running aground, being stranded, grounding, beaching"], "kun reading compounds": ""}