{"character": "飲", "strokes": "12", "radical": "食", "radical variants": ["飠"], "radical meaning": ["eat", "food"], "parts": ["欠", "食"], "kanji_variants": ["飮"], "meanings": ["drink", "smoke", "take"], "kun": ["の.む", "-の.み"], "on": ["イン", "オン"], "nanori readings": "", "grade": "Jōyō kanji, taught in grade 3", "jlpt": "N4", "frequency": "969", "on reading compounds": ["飲【イン】drinking (sometimes esp. alcohol), drink, drinking party", "飲酒【インシュ】drinking alcohol (sake)", "留飲【リュウイン】gloating, satisfaction", "暴飲【ボウイン】heavy drinking", "飲食【インショク】food and drink, eating and drinking"], "kun reading compounds": ["飲む【のむ】to drink, to gulp, to swallow, to take (medicine), to smoke (tobacco), to engulf, to overwhelm, to keep down, to suppress, to accept (e.g. demand, condition), to make light of, to conceal", "飲む打つ買う【のむうつかう】drinking, gambling, and buying women in prostitution"]}