{"character": "刹", "strokes": "8", "radical": "刀", "radical variants": ["刂"], "radical meaning": ["knife", "sword"], "parts": ["丶", "ノ", "刈", "木"], "kanji_variants": "", "meanings": ["temple"], "kun": "", "on": ["セチ", "セツ", "サツ"], "nanori readings": "", "grade": "Jōyō kanji, taught in junior high", "jlpt": "", "frequency": "", "on reading compounds": ["刹【サツ】temple (Buddhist), central pillar of a pagoda, kshetra (realm, country), ksetra", "刹那【セツナ】moment, instant, kshana, duration of a single mental event (about 1/75 second), shortest possible interval of time", "十刹【ジッサツ】ten important Rinzai temples, second in significance to the Kyoto Gozan", "仏刹【ブッサツ】Buddhist temple", "刹【サツ】temple (Buddhist), central pillar of a pagoda, kshetra (realm, country), ksetra", "名刹【メイサツ】famous temple", "古刹【コサツ】ancient temple"], "kun reading compounds": ""}