{"character": "唳", "strokes": "10", "radical": "口", "radical variants": [], "radical meaning": ["mouth", "opening"], "parts": ["一", "口", "大", "尸", "戸"], "kanji_variants": "", "meanings": ["cry", "honking of birds", "droning of cicadas"], "kun": ["れつ"], "on": ["レイ"], "nanori readings": "", "grade": "", "jlpt": "", "frequency": "", "on reading compounds": ["風声鶴唳【フウセイカクレイ】getting frightened even by a slight noise, hearing the enemy in every leaf that rustles, being afraid of one's own shadow"], "kun reading compounds": ""}