{"character": "埜", "strokes": "11", "radical": "土", "radical variants": [], "radical meaning": ["earth"], "parts": ["土", "木"], "kanji_variants": ["野", "壄"], "meanings": ["open country", "field", "wilderness"], "kun": ["の"], "on": ["ヤ", "ショ"], "nanori readings": "", "grade": "Jinmeiyō kanji, used in names", "jlpt": "", "frequency": "", "on reading compounds": ["野【ノ】plain, field, hidden (structural) member, wild, lacking a political post"], "kun reading compounds": ["野【の】plain, field, hidden (structural) member, wild, lacking a political post"]}