{"character": "孰", "strokes": "11", "radical": "子", "radical variants": [], "radical meaning": ["child", "seed"], "parts": ["丶", "亠", "九", "口", "子"], "kanji_variants": "", "meanings": ["which", "how", "who"], "kun": ["いずれ", "たれ"], "on": ["ジュク"], "nanori readings": "", "grade": "", "jlpt": "", "frequency": "", "on reading compounds": "", "kun reading compounds": ["何れ【いずれ】where, which, who, anyway, anyhow, at any rate, sooner or later, eventually, one of these days, at some future date or time, both, either, any, all, whichever", "何れか【いずれか】any of, either of, (to) any"]}