{"character": "廊", "strokes": "12(also11)", "radical": "广", "radical variants": [], "radical meaning": ["house on cliff"], "parts": ["广", "邦", "艮"], "kanji_variants": "", "meanings": ["corridor", "hall", "tower"], "kun": "", "on": ["ロウ"], "nanori readings": "", "grade": "Jōyō kanji, taught in junior high", "jlpt": "N1", "frequency": "1598", "on reading compounds": ["廊【ロウ】corridor, passage, hall", "廊下【ロウカ】corridor, hallway, passageway", "回廊【カイロウ】corridor, gallery, hallway, cloister (i.e. covered walk typically circling a building or garden, esp. in a palace or place of worship)", "ポーランド回廊【ポーランドカイロウ】Polish Corridor"], "kun reading compounds": ""}