{"character": "彿", "strokes": "8", "radical": "彳", "radical variants": [], "radical meaning": ["step"], "parts": ["｜", "ノ", "弓", "彳"], "kanji_variants": ["髴"], "meanings": ["dimly"], "kun": "", "on": ["フツ"], "nanori readings": "", "grade": "", "jlpt": "", "frequency": "", "on reading compounds": ["彷彿【ホウフツ】(bearing a) close resemblance, vivid reminder (e.g. of the past), dim, faint, vague, blurred", "水天彷彿【スイテンホウフツ】view in the distant offing where the sea and skyline cannot be distinguished"], "kun reading compounds": ""}