{"character": "怯", "strokes": "8", "radical": "心", "radical variants": ["忄", "⺗"], "radical meaning": ["heart"], "parts": ["厶", "土", "忙"], "kanji_variants": "", "meanings": ["cowardice", "wince", "flinch", "hesitate", "waver"], "kun": ["ひる.む", "おびえ.る", "おじる", "おび.える", "おそ.れる"], "on": ["キョウ", "コウ"], "nanori readings": "", "grade": "", "jlpt": "", "frequency": "", "on reading compounds": ["怯弱【キョウジャク】coward", "怯懦【キョウダ】cowardice"], "kun reading compounds": ["怯む【ひるむ】to falter, to flinch (from), to recoil (from), to quail (at)", "怯える【おびえる】to become frightened, to be frightened (of), to be scared (of)", "怯える【おびえる】to become frightened, to be frightened (of), to be scared (of)"]}