{"character": "捏", "strokes": "10", "radical": "手", "radical variants": ["扌", "龵"], "radical meaning": ["hand"], "parts": ["土", "扎", "日"], "kanji_variants": "", "meanings": ["knead", "mix"], "kun": ["こ.ねる", "ね.る", "つく.ねる"], "on": ["ネツ", "テツ", "ネチ"], "nanori readings": "", "grade": "", "jlpt": "", "frequency": "", "on reading compounds": ["捏造【ネツゾウ】fabrication, forgery, falsehood, hoax", "捏造記事【ネツゾウキジ】fabricated story, cooked up (news) report"], "kun reading compounds": ["捏ねる【こねる】to knead, to mix with fingers, to quibble, to argue for argument's sake"]}