{"character": "満", "strokes": "12", "radical": "水", "radical variants": ["氵", "氺"], "radical meaning": ["water"], "parts": ["一", "｜", "二", "冂", "山", "汁", "艾"], "kanji_variants": ["滿"], "meanings": ["full", "fullness", "enough", "satisfy"], "kun": ["み.ちる", "み.つ", "み.たす"], "on": ["マン", "バン"], "nanori readings": ["ま", "みち", "みつ", "みつる"], "grade": "Jōyō kanji, taught in grade 4", "jlpt": "N3", "frequency": "515", "on reading compounds": ["満【マン】being full, (counting) completed years (e.g. when calculating age), full (years, months, etc.), Manchuria", "満員【マンイン】full house, no vacancy, sold out, standing room only, full (of people), crowded", "豊満【ホウマン】stout, corpulent, plump, voluptuous", "倍満【バイマン】win worth 16000 points (or, if dealer, 24000 points)"], "kun reading compounds": ["満ちる【みちる】to be full, to wax (e.g. moon), to rise (e.g. tide), to mature, to expire", "満つ【みつ】to be full, to wax (e.g. moon), to rise (e.g. tide), to mature, to expire", "満たす【みたす】to satisfy (conditions, one's appetite, etc.), to meet (e.g. demands), to fulfill, to gratify, to fill (e.g. a cup), to pack, to supply"]}