{"character": "滝", "strokes": "13", "radical": "水", "radical variants": ["氵", "氺"], "radical meaning": ["water"], "parts": ["汁", "田", "立", "竜"], "kanji_variants": ["瀧"], "meanings": ["waterfall", "rapids", "cascade"], "kun": ["たき"], "on": ["ロウ", "ソウ"], "nanori readings": ["らき"], "grade": "Jōyō kanji, taught in junior high", "jlpt": "N1", "frequency": "1478", "on reading compounds": "", "kun reading compounds": ["滝【たき】waterfall, rapids", "滝川【たきがわ】rapids", "小滝【おたき】cascade", "白滝【しらたき】shirataki noodles, white noodles made from konjak starch, often used in sukiyaki, waterfall resembling a white sheet"]}