{"character": "潮", "strokes": "15", "radical": "水", "radical variants": ["氵", "氺"], "radical meaning": ["water"], "parts": ["十", "汁", "日", "月"], "kanji_variants": "", "meanings": ["tide", "salt water", "opportunity"], "kun": ["しお", "うしお"], "on": ["チョウ"], "nanori readings": ["いた"], "grade": "Jōyō kanji, taught in grade 6", "jlpt": "N1", "frequency": "1231", "on reading compounds": ["潮流【チョウリュウ】tide, tidal current, tendency, drift, trend", "潮位【チョウイ】tide level", "思潮【シチョウ】trend of thought", "退潮【タイチョウ】ebb tide, waning fortunes"], "kun reading compounds": ["潮【しお】tide, current, sea water, opportunity, chance, thin soup of fish or shellfish boiled in seawater", "潮風【しおかぜ】salty sea breeze, salt wind", "黒潮【くろしお】Japan Current, Kuroshio Current", "赤潮【あかしお】red tide", "潮【しお】tide, current, sea water, opportunity, chance, thin soup of fish or shellfish boiled in seawater", "潮汁【うしおじる】thin soup of fish or shellfish boiled in seawater", "夕潮【ゆうしお】evening tide"]}