{"character": "瓏", "strokes": "20", "radical": "玉", "radical variants": ["王"], "radical meaning": ["jade (king)"], "parts": ["月", "王", "立"], "kanji_variants": "", "meanings": ["clarity", "sound of jewels"], "kun": "", "on": ["ロウ"], "nanori readings": "", "grade": "", "jlpt": "", "frequency": "", "on reading compounds": ["玲瓏【レイロウ】clear, translucent, brilliant, sweetly ringing (as the tinklings of jade)", "八面玲瓏【ハチメンレイロウ】beautiful from all sides, perfect serenity, affability"], "kun reading compounds": ""}