{"character": "甥", "strokes": "12(also13)", "radical": "生", "radical variants": [], "radical meaning": ["life"], "parts": ["力", "生", "田"], "kanji_variants": "", "meanings": ["nephew"], "kun": ["おい", "むこ"], "on": ["セイ", "ソウ", "ショウ"], "nanori readings": "", "grade": "Jinmeiyō kanji, used in names", "jlpt": "", "frequency": "", "on reading compounds": ["甥姪【オイメイ】nephews and nieces", "令甥【レイセイ】your nephew"], "kun reading compounds": ["甥【おい】nephew", "甥御【おいご】(another person's) nephew", "又甥【またおい】grandnephew"]}