{"character": "穗", "strokes": "17", "radical": "禾", "radical variants": [], "radical meaning": ["grain"], "parts": ["心", "日", "禾", "虫"], "kanji_variants": ["穂"], "meanings": ["ear (of grain)", "head", "crest (of wave)"], "kun": ["ほ"], "on": ["スイ"], "nanori readings": ["お"], "grade": "Jinmeiyō kanji, used in names", "jlpt": "", "frequency": "", "on reading compounds": "", "kun reading compounds": ["穂【ほ】ear (of plant), head (of plant), point, tip, scion (in grafting), cion", "初穂【はつほ】first ears of rice of the season, first crops of the season, first harvest of the season, offering (to the gods)"]}