{"character": "竦", "strokes": "12", "radical": "立", "radical variants": [], "radical meaning": ["stand", "erect"], "parts": ["｜", "并", "口", "木", "立"], "kanji_variants": "", "meanings": ["crouch", "cower"], "kun": ["すく.む", "おそ.れる", "つつし.む"], "on": ["ショウ"], "nanori readings": "", "grade": "", "jlpt": "", "frequency": "", "on reading compounds": ["悚然【ショウゼン】terrified, horrified"], "kun reading compounds": ["竦む【すくむ】to freeze (from fear, etc.), to be unable to move (e.g. from surprise), to be paralyzed (with horror, etc.), to cower, to shrink in on oneself"]}