{"character": "筌", "strokes": "12", "radical": "竹", "radical variants": ["⺮"], "radical meaning": ["bamboo"], "parts": ["个", "王", "竹", "乞"], "kanji_variants": "", "meanings": ["fish trap", "weir"], "kun": ["うけ", "うえ"], "on": ["セン"], "nanori readings": "", "grade": "", "jlpt": "", "frequency": "", "on reading compounds": ["筌【ウエ】cylindrical bamboo fishing basket", "茶筅【チャセン】tea whisk, bamboo whisk for making Japanese tea, hair style where the hair is tied up in a bundle on the back of the head (resembling the shape of a tea whisk)"], "kun reading compounds": ["筌【うえ】cylindrical bamboo fishing basket", "筌【うえ】cylindrical bamboo fishing basket"]}