{"character": "篦", "strokes": "16", "radical": "竹", "radical variants": ["⺮"], "radical meaning": ["bamboo"], "parts": ["囗", "比", "竹", "乞"], "kanji_variants": ["箆"], "meanings": ["spatula", "arrow shaft"], "kun": ["へら", "の"], "on": ["ヘイ", "ハイ"], "nanori readings": "", "grade": "", "jlpt": "", "frequency": "", "on reading compounds": "", "kun reading compounds": ["箆【へら】spatula, (artificially cultured) Japanese crucian carp", "箆鹿【へらじか】moose (Alces alces), elk", "箆【の】shaft (of an arrow), arrow bamboo (Pseudosasa japonica)", "野太い【のぶとい】audacious, daring, bold, impudent, cheeky, throaty (voice), rough, deep, hoarse"]}