{"character": "纂", "strokes": "20", "radical": "竹", "radical variants": ["⺮"], "radical meaning": ["bamboo"], "parts": ["小", "幺", "目", "竹", "糸", "乞"], "kanji_variants": "", "meanings": ["editing", "compiling"], "kun": ["あつ.める"], "on": ["サン"], "nanori readings": "", "grade": "Jinmeiyō kanji, used in names", "jlpt": "", "frequency": "", "on reading compounds": ["纂述【サンジュツ】gathering and writing up material", "簒奪【サンダツ】usurpation", "類纂【ルイサン】collection of similar objects, classification by similarity", "雑纂【ザッサン】miscellaneous collection"], "kun reading compounds": ""}