{"character": "臈", "strokes": "16", "radical": "肉", "radical variants": ["⺼"], "radical meaning": ["meat"], "parts": ["勹", "匕", "艾", "日", "月"], "kanji_variants": ["臘"], "meanings": ["year-end sacrifice", "dried meat"], "kun": "", "on": ["ロウ"], "nanori readings": "", "grade": "", "jlpt": "", "frequency": "", "on reading compounds": ["臈【ロウ】year in the Buddhist order (after the completion of the first meditation retreat), becoming more experienced with age, social status based on this experience", "臈たける【ロウタケル】to be elegant (usu. of a woman), to be graceful, to be refined, to become well-experienced, to mature", "女郎【ジョロウ】prostitute (esp. Edo period)", "劫臈【コウロウ】long time, long years of service"], "kun reading compounds": ""}