{"character": "荊", "strokes": "9", "radical": "艸", "radical variants": ["艹"], "radical meaning": ["grass"], "parts": ["一", "ノ", "二", "刈", "廾", "艾"], "kanji_variants": "", "meanings": ["thorn", "brier", "whip"], "kun": ["いばら"], "on": ["ケイ"], "nanori readings": "", "grade": "", "jlpt": "", "frequency": "", "on reading compounds": ["荊冠【ケイカン】crown of thorns", "荊棘【ケイキョク】wild rose, bramble, briar patch, obstacle, source of difficulty, thorn"], "kun reading compounds": ["茨【いばら】thorny shrub, wild rose, briar, thorn, cusp"]}