{"character": "蓼", "strokes": "14", "radical": "艸", "radical variants": ["艹"], "radical meaning": ["grass"], "parts": ["个", "冫", "彡", "艾", "羽"], "kanji_variants": [], "meanings": ["luxurious grass", "a smartweed"], "kun": ["たで"], "on": ["シン", "リク", "リョウ"], "nanori readings": "", "grade": "", "jlpt": "", "frequency": "2447", "on reading compounds": ["仙蓼【センリョウ】Chloranthus glaber", "木天蓼【マタタビ】silver vine (Actinidia polygama), cat powder"], "kun reading compounds": ["蓼【たで】knotweed (Polygonaceae), jointweed, smartweed, water pepper (Persicaria hydropiper)", "蓼藍【たであい】dyer's knotweed (Persicaria tinctoria, used to produce indigo dye)", "藍蓼【あいたで】dyer's knotweed (Persicaria tinctoria, used to produce indigo dye)", "柳蓼【やなぎたで】water pepper (Persicaria hydropiper)"]}