{"character": "裃", "strokes": "11", "radical": "衣", "radical variants": ["衤"], "radical meaning": ["clothes"], "parts": ["卜", "初"], "kanji_variants": "", "meanings": ["old ceremonial garb", "samurai garb", "(kokuji)"], "kun": ["かみしも"], "on": "", "nanori readings": "", "grade": "", "jlpt": "", "frequency": "", "on reading compounds": "", "kun reading compounds": ["裃【かみしも】samurai costume, old ceremonial costume, top and bottom, up and down, high and low, above and below, upper and lower ends", "水上下【みずかみしも】light blue samurai costume commonly worn when committing suicide"]}