{"character": "贋", "strokes": "19", "radical": "厂", "radical variants": [], "radical meaning": ["cliff"], "parts": ["化", "ハ", "厂", "目", "貝", "隹"], "kanji_variants": "", "meanings": ["counterfeit", "forgery"], "kun": ["にせ"], "on": ["ガン"], "nanori readings": "", "grade": "", "jlpt": "", "frequency": "2439", "on reading compounds": ["偽物【ニセモノ】spurious article, forgery, counterfeit, imitation, sham", "贋作【ガンサク】fake (work), counterfeit"], "kun reading compounds": ["偽【にせ】imitation, fake, phony, counterfeit, forged, bogus, sham, pseudo-", "偽物【にせもの】spurious article, forgery, counterfeit, imitation, sham"]}