{"character": "鑿", "strokes": "28", "radical": "金", "radical variants": ["釒"], "radical meaning": ["metal", "gold"], "parts": ["并", "几", "又", "干", "殳", "臼", "金"], "kanji_variants": "", "meanings": ["chisel"], "kun": ["のみ", "うが.つ"], "on": ["サク"], "nanori readings": "", "grade": "", "jlpt": "", "frequency": "", "on reading compounds": ["鑿岩機【サクガンキ】rock drill, pneumatic drill, jackhammer", "鑿井【サクセイ】well drilling", "掘削【クッサク】digging out, excavation", "開削【カイサク】excavation, cutting, digging"], "kun reading compounds": ["鑿【のみ】chisel", "鎬鑿【しのぎのみ】chisel for making dovetail joints", "平鑿【ひらのみ】flat chisel"]}