{"character": "雉", "strokes": "13", "radical": "隹", "radical variants": [], "radical meaning": ["small bird"], "parts": ["矢", "隹", "乞"], "kanji_variants": "", "meanings": ["pheasant"], "kun": ["きじ"], "on": ["ジ", "チ"], "nanori readings": ["き"], "grade": "", "jlpt": "", "frequency": "", "on reading compounds": ["高麗雉【コウライキジ】common pheasant (Phasianus colchicus), ring-necked pheasant", "白雉【ハクチ】Hakuchi era (650.2.15-654.10.?)"], "kun reading compounds": ["雉【きじ】green pheasant (Phasianus versicolor), Japanese pheasant", "キジ科【キジか】Phasianidae, pheasant family of birds", "高麗雉【こうらいきじ】common pheasant (Phasianus colchicus), ring-necked pheasant"]}