{"character": "鮠", "strokes": "17", "radical": "魚", "radical variants": [], "radical meaning": ["fish"], "parts": ["卩", "厂", "杰", "田", "魚"], "kanji_variants": "", "meanings": ["dace (carp)", "(kokuji)"], "kun": ["はえ", "はや"], "on": ["カイ", "ゲ", "ガイ"], "nanori readings": "", "grade": "", "jlpt": "", "frequency": "", "on reading compounds": "", "kun reading compounds": ["鮠【はや】minnow, shinner", "鮠【はや】minnow, shinner", "高鮠【たかはや】Chinese minnow (Phoxinus oxycephalus)", "油鮠【あぶらはや】Amur minnow (Phoxinus logowskii steindachneri)"]}