{"character": "勘", "strokes": "11", "radical": "力", "radical variants": [], "radical meaning": ["power", "force"], "parts": ["儿", "力", "匚", "甘"], "kanji_variants": "", "meanings": ["intuition", "perception", "check", "compare", "sixth sense"], "kun": "", "on": ["カン"], "nanori readings": ["か", "さとる"], "grade": "Jōyō kanji, taught in junior high", "jlpt": "N1", "frequency": "1494", "on reading compounds": ["勘【カン】perception, intuition, the sixth sense", "勘案【カンアン】taking into consideration, giving consideration (to)", "勅勘【チョッカン】the emperor's censure", "山勘【ヤマカン】guesswork, speculation, hunch"], "kun reading compounds": ""}