{"character": "嗅", "strokes": "13", "radical": "口", "radical variants": [], "radical meaning": ["mouth", "opening"], "parts": ["口", "大", "犬", "目", "自"], "kanji_variants": ["齅"], "meanings": ["smell", "sniff", "scent"], "kun": ["か.ぐ"], "on": ["キュウ"], "nanori readings": "", "grade": "Jōyō kanji, taught in junior high", "jlpt": "", "frequency": "2480", "on reading compounds": ["嗅覚【キュウカク】sense of smell, olfaction", "嗅覚受容神経【キュウカクジュヨウシンケイ】olfactory receptor neuron"], "kun reading compounds": ["嗅ぐ【かぐ】to sniff, to smell"]}