{"character": "渉", "strokes": "11", "radical": "水", "radical variants": ["氵", "氺"], "radical meaning": ["water"], "parts": ["ノ", "小", "汁", "止"], "kanji_variants": [], "meanings": ["ford", "go cross", "transit", "ferry", "import", "involve"], "kun": ["わた.る"], "on": ["ショウ"], "nanori readings": ["えん"], "grade": "Jōyō kanji, taught in junior high", "jlpt": "N1", "frequency": "499", "on reading compounds": ["渉外【ショウガイ】public relations, client liaison, client relations", "渉外係【ショウガイガカリ】liaison officer, public relations man", "団体交渉【ダンタイコウショウ】collective bargaining", "婚外交渉【コンガイコウショウ】extramarital sex"], "kun reading compounds": ["渡る【わたる】to cross over, to go across, to extend, to cover, to range, to span"]}