{"character": "盤", "strokes": "15", "radical": "皿", "radical variants": [], "radical meaning": ["dish"], "parts": ["几", "又", "殳", "皿", "舟"], "kanji_variants": "", "meanings": ["tray", "shallow bowl", "platter", "tub", "board", "phonograph record"], "kun": "", "on": ["バン"], "nanori readings": ["ち", "わ"], "grade": "Jōyō kanji, taught in junior high", "jlpt": "N1", "frequency": "881", "on reading compounds": ["盤【バン】disk, disc, record, clock face, tray, shallow bowl, grid, board (e.g. in shogi)", "盤谷【バンコク】Bangkok (Thailand)", "地盤【ジバン】ground, crust (earth), bed (gravel, river, etc.), foundation (building, etc.), base, constituency, power base, support (electoral), footing, foothold", "中盤【チュウバン】middle stage, middle phase, middle game, midfield"], "kun reading compounds": ""}