{"character": "鍋", "strokes": "17", "radical": "金", "radical variants": ["釒"], "radical meaning": ["metal", "gold"], "parts": ["冂", "口", "金"], "kanji_variants": "", "meanings": ["pot", "pan", "kettle"], "kun": ["なべ"], "on": ["カ"], "nanori readings": "", "grade": "Jōyō kanji, taught in junior high", "jlpt": "", "frequency": "1810", "on reading compounds": "", "kun reading compounds": ["鍋【なべ】saucepan, pot, stew, hot pot", "鍋物【なべもの】stew, food cooked in a pot", "もつ鍋【もつなべ】hot pot stew made with offal, vegetables and (often) miso", "土鍋【どなべ】earthenware pot"]}