{"character": "霜", "strokes": "17", "radical": "雨", "radical variants": [], "radical meaning": ["rain"], "parts": ["木", "目", "雨"], "kanji_variants": "", "meanings": ["frost"], "kun": ["しも"], "on": ["ソウ"], "nanori readings": "", "grade": "Jōyō kanji, taught in junior high", "jlpt": "N1", "frequency": "2151", "on reading compounds": ["霜害【ソウガイ】frost damage", "霜剣【ソウケン】cold sharp sword, blade of ice", "星霜【セイソウ】years, time", "幾星霜【イクセイソウ】many months and years"], "kun reading compounds": ["霜【しも】frost", "霜降り【しもふり】speckled with white, salt-and-pepper (pattern, fabric, etc.), marbling (of beef), (of fish, chicken, shellfish, etc.) blanching by exposure to boiling and then icy water, formation of frost", "朝霜【あさしも】morning frost", "露霜【つゆじも】frozen dew, frost and dew, years, time"]}