{"character": "絞", "strokes": "12", "radical": "糸", "radical variants": ["糹"], "radical meaning": ["silk"], "parts": ["亠", "小", "幺", "父", "糸"], "kanji_variants": "", "meanings": ["strangle", "constrict", "wring"], "kun": ["しぼ.る", "し.める", "し.まる"], "on": ["コウ"], "nanori readings": "", "grade": "Jōyō kanji, taught in junior high", "jlpt": "N1", "frequency": "1288", "on reading compounds": ["絞首刑【コウシュケイ】death by hanging, execution by hanging", "絞殺【コウサツ】strangulation, strangling"], "kun reading compounds": ["絞る【しぼる】to wring (towel, rag), to squeeze, to squeeze (fruit to extract juice), to press, to extract, to milk, to express milk, to rack (one's brains), to strain (one's voice), to extort, to exploit, to chew out, to reprimand severely, to rake over the coals, to give a sound scolding, to tell someone off, to scold, to rebuke, to drill into, to train, to narrow down (one's focus), to whittle down, to gather up (curtain, etc.), to tighten (drawstring), to stop down (lens), to turn down (e.g. radio), to bend (bow), to draw, to hold down, to constrict, to immobilize", "絞める【しめる】to strangle, to constrict", "絞まる【しまる】to be strangled, to be constricted"]}