{"character": "誕", "strokes": "15", "radical": "言", "radical variants": ["訁"], "radical meaning": ["speech"], "parts": ["ノ", "廴", "止", "言"], "kanji_variants": "", "meanings": ["nativity", "be born", "declension", "lie", "be arbitrary"], "kun": "", "on": ["タン"], "nanori readings": "", "grade": "Jōyō kanji, taught in grade 6", "jlpt": "N1", "frequency": "1024", "on reading compounds": ["誕生【タンジョウ】birth, creation, formation", "誕生日【タンジョウビ】birthday", "生誕【セイタン】birth, nativity", "再誕【サイタン】resurrection (of a company or school, etc.)"], "kun reading compounds": ""}