{"character": "偉", "strokes": "12", "radical": "人", "radical variants": ["亻"], "radical meaning": ["man", "human"], "parts": ["化", "口", "韋"], "kanji_variants": "", "meanings": ["admirable", "greatness", "remarkable", "conceited", "famous", "excellent"], "kun": ["えら.い"], "on": ["イ"], "nanori readings": ["ひで"], "grade": "Jōyō kanji, taught in junior high", "jlpt": "N3", "frequency": "1639", "on reading compounds": ["偉【イ】greatness", "偉業【イギョウ】great achievement, great feat, great work, great undertaking", "魁偉【カイイ】brawny, muscular, impressive, gigantic", "容貌魁偉【ヨウボウカイイ】(a man) having a commanding face and a powerful physique"], "kun reading compounds": ["偉い【えらい】great, excellent, admirable, remarkable, distinguished, important, celebrated, famous, eminent, very troublesome, awful, terrible, tiring, tough, very, extremely", "偉いこっちゃ【えらいこっちゃ】What are we going to do?, uh-oh, oh crap"]}