{"character": "毛", "strokes": "4", "radical": "毛", "radical variants": [], "radical meaning": ["fur", "hair"], "parts": ["毛"], "kanji_variants": "", "meanings": ["fur", "hair", "feather", "down"], "kun": ["け"], "on": ["モウ"], "nanori readings": ["めん", "も"], "grade": "Jōyō kanji, taught in grade 2", "jlpt": "N2", "frequency": "1179", "on reading compounds": ["毛【モウ】one-thousandth, 0.03 mm (one-thousandth of a sun), 0.01 percent (one-thousandth of a wari), 3.75 milligrams (one-thousandth of a monme), old monetary unit (0.0001 yen)", "毛皮【ケガワ】fur, skin, pelt, kanji \"fur\" radical", "不毛【フモウ】barren, sterile, infertile, unproductive (e.g. discussion), fruitless", "再生毛【サイセイモウ】recycled wool, reclaimed wool"], "kun reading compounds": ["毛【け】hair, fur, wool, down, plumage, feathers", "毛皮【けがわ】fur, skin, pelt, kanji \"fur\" radical", "お毛々【おけけ】pubic hair", "猫っ毛【ねこっけ】fine, soft hair"]}