{"character": "番", "strokes": "12", "radical": "田", "radical variants": [], "radical meaning": ["field"], "parts": ["田", "米", "釆"], "kanji_variants": "", "meanings": ["turn", "number in a series"], "kun": ["つが.い"], "on": ["バン"], "nanori readings": ["は", "ま"], "grade": "Jōyō kanji, taught in grade 2", "jlpt": "N3", "frequency": "348", "on reading compounds": ["番【バン】number (in a series), (one's) turn, watch, guard, lookout, bout, match", "番組【バングミ】program (e.g. TV), programme", "出番【デバン】one's turn, one's shift, one's turn on stage, screen time, screentime", "春一番【ハルイチバン】first storm of spring, strong winds during the change from winter to spring"], "kun reading compounds": ["番い【つがい】pair (esp. of mated animals), brace, couple, (anatomical) joint", "つがい目【つがいめ】joint, hinge", "手番【てつがい】plan, arrangements"]}